django_aws_alb_idp_auth/__init__.py
django_aws_alb_idp_auth/backends.py
django_aws_alb_idp_auth/identifier.py
django_aws_alb_idp_auth/middleware.py
django_aws_alb_idp_auth-0.1.3.dist-info/LICENSE
django_aws_alb_idp_auth-0.1.3.dist-info/METADATA
django_aws_alb_idp_auth-0.1.3.dist-info/WHEEL
django_aws_alb_idp_auth-0.1.3.dist-info/RECORD
