Metadata-Version: 2.1
Name: django-aws-alb-idp-auth
Version: 0.1.3
Summary: 
License: MIT
Author: Atsushi Odagiri
Author-email: aodagx@gmail.com
Maintainer: Takanao Endoh
Maintainer-email: djmchl@gmail.com
Requires-Python: >=3.8,<4.0
Classifier: License :: OSI Approved :: MIT License
Classifier: Programming Language :: Python :: 3
Classifier: Programming Language :: Python :: 3.8
Classifier: Programming Language :: Python :: 3.9
Classifier: Programming Language :: Python :: 3.10
Classifier: Programming Language :: Python :: 3.11
Classifier: Programming Language :: Python :: 3.12
Requires-Dist: Django (>=3.0.0,<5)
Requires-Dist: PyJWT[crypto] (>=2.0.1,<3.0.0)
